example_template_core/__init__.py
example_template_core/utils.py
example_template_core/version.py
example_template_core-0.1.0.dist-info/LICENSE.txt
example_template_core-0.1.0.dist-info/WHEEL
example_template_core-0.1.0.dist-info/METADATA
example_template_core-0.1.0.dist-info/RECORD
